stdinutils/__init__.py
stdinutils/__main__.py
stdinutils-0.1.0.dist-info/COPYING
stdinutils-0.1.0.dist-info/WHEEL
stdinutils-0.1.0.dist-info/METADATA
stdinutils-0.1.0.dist-info/RECORD
