Metadata-Version: 2.1
Name: stdinutils
Version: 0.1.0
Summary: 
Author: 4thel00z
Author-email: 4thel00z@gmail.com
Requires-Python: >=3.9,<4.0
Classifier: Programming Language :: Python :: 3
Classifier: Programming Language :: Python :: 3.9
